convoys/__init__.py
convoys/export.py
convoys/multi.py
convoys/plotting.py
convoys/py.typed
convoys/regression.py
convoys/single.py
convoys/utils.py
convoys2-0.4.0.dist-info/METADATA
convoys2-0.4.0.dist-info/WHEEL
convoys2-0.4.0.dist-info/licenses/LICENSE
convoys2-0.4.0.dist-info/RECORD
