Metadata-Version: 2.4
Name: convoys2
Version: 0.4.0
Summary: Implementation of statistical models to analyze time lagged conversions
Author-email: Erik Bernhardsson <erikbern@better.com>, Ted Conbeer <tconbeer@users.noreply.github.com>
License-File: LICENSE
Requires-Python: <3.14,>=3.12
Requires-Dist: autograd-gamma>=0.2.0
Requires-Dist: autograd>=1.7.0
Requires-Dist: emcee>=3.0.0
Requires-Dist: matplotlib>=2.0.0
Requires-Dist: numpy<3,>=2.0.0
Requires-Dist: pandas>=0.24.0
Requires-Dist: progressbar2>=3.46.1
Requires-Dist: scipy<2,>=1.15.0
